itunespy/__init__.py
itunespy/artist.py
itunespy/ebook_artist.py
itunespy/movie_artist.py
itunespy/music_album.py
itunespy/music_artist.py
itunespy/result_item.py
itunespy/track.py
itunespy-1.6.1.dist-info/LICENSE
itunespy-1.6.1.dist-info/METADATA
itunespy-1.6.1.dist-info/WHEEL
itunespy-1.6.1.dist-info/top_level.txt
itunespy-1.6.1.dist-info/RECORD
